Metadata-Version: 1.1
Name: BacGenomePipeline
Version: 1.0.8
Summary: Complete Bacterial Genome Assembly and Annotation Pipeline
Home-page: https://github.com/StephenFordham/BacGenomePipeline
Author: Stephen Fordham
Author-email: sfstephenfordham@gmail.com
License: MIT
Keywords: Genome Assembly,WGS,bacterial pipeline,prokaryotic,bacterial genome assembly
Platform: UNKNOWN
Classifier: Development Status :: 4 - Beta
Classifier: Intended Audience :: Education
Classifier: Operating System :: POSIX :: Linux
Classifier: License :: OSI Approved :: MIT License
Classifier: Programming Language :: Python :: 3
